backend/.coveragerc
backend/.gitignore
backend/Dockerfile
backend/Dockerfile.base
backend/README.md
backend/__init__.py
backend/api/__init__.py
backend/api/dependencies.py
backend/api/routes/__init__.py
backend/api/routes/admin.py
backend/api/routes/audio_search.py
backend/api/routes/auth.py
backend/api/routes/file_upload.py
backend/api/routes/health.py
backend/api/routes/internal.py
backend/api/routes/jobs.py
backend/api/routes/push.py
backend/api/routes/rate_limits.py
backend/api/routes/review.py
backend/api/routes/tenant.py
backend/api/routes/themes.py
backend/api/routes/users.py
backend/config.py
backend/exceptions.py
backend/main.py
backend/middleware/__init__.py
backend/middleware/audit_logging.py
backend/middleware/tenant.py
backend/models/__init__.py
backend/models/job.py
backend/models/requests.py
backend/models/tenant.py
backend/models/theme.py
backend/models/user.py
backend/models/worker_log.py
backend/pyproject.toml
backend/quick-check.sh
backend/requirements.txt
backend/run_tests.sh
backend/services/__init__.py
backend/services/audio_analysis_service.py
backend/services/audio_editing_service.py
backend/services/audio_search_service.py
backend/services/auth_service.py
backend/services/credential_manager.py
backend/services/discord_service.py
backend/services/dropbox_service.py
backend/services/email_service.py
backend/services/email_validation_service.py
backend/services/encoding_interface.py
backend/services/encoding_service.py
backend/services/firestore_service.py
backend/services/flacfetch_client.py
backend/services/gce_encoding/README.md
backend/services/gce_encoding/__init__.py
backend/services/gce_encoding/main.py
backend/services/gce_encoding/requirements.txt
backend/services/gdrive_service.py
backend/services/job_defaults_service.py
backend/services/job_logging.py
backend/services/job_manager.py
backend/services/job_notification_service.py
backend/services/langfuse_preloader.py
backend/services/local_encoding_service.py
karaoke_gen-0.114.15.dist-info/METADATA
karaoke_gen-0.114.15.dist-info/WHEEL
karaoke_gen-0.114.15.dist-info/entry_points.txt
karaoke_gen-0.114.15.dist-info/licenses/LICENSE
karaoke_gen-0.114.15.dist-info/RECORD
