Metadata-Version: 2.4
Name: karaoke-gen
Version: 0.114.15
Summary: Generate karaoke videos with synchronized lyrics. Handles the entire process from downloading audio and lyrics to creating the final video with title screens.
License: MIT
License-File: LICENSE
Author: Andrew Beveridge
Author-email: andrew@beveridge.uk
Requires-Python: >=3.10,<3.14
Classifier: License :: OSI Approved :: MIT License
Classifier: Programming Language :: Python :: 3
Classifier: Programming Language :: Python :: 3.10
Classifier: Programming Language :: Python :: 3.11
Classifier: Programming Language :: Python :: 3.12
Classifier: Programming Language :: Python :: 3.13
Provides-Extra: dev
Provides-Extra: local-whisper
Requires-Dist: aiohttp (>=3.13.2,<4.0.0)
Requires-Dist: argparse (>=1.4.0)
Requires-Dist: attrs (>=24.2.0)
Requires-Dist: audio-separator[cpu] (>=0.34.0)
Requires-Dist: beautifulsoup4 (>=4)
Requires-Dist: black (>=23) ; extra == "dev"
Requires-Dist: cattrs (>=24.1.2)
Requires-Dist: dropbox (>=12)
Requires-Dist: email-validator (>=2.0.0)
Requires-Dist: fastapi (>=0.104.0)
Requires-Dist: fetch-lyrics-from-genius (>=0.1)
Requires-Dist: ffmpeg-python (>=0.2.0,<0.3.0)
Requires-Dist: flacfetch (>=0.9.0)
Requires-Dist: fonttools (>=4.55)
Requires-Dist: google-api-python-client
Requires-Dist: google-auth
Requires-Dist: google-auth-httplib2
Requires-Dist: google-auth-oauthlib
Requires-Dist: google-cloud-firestore (>=2.14.0)
Requires-Dist: google-cloud-run (>=0.10.0)
Requires-Dist: google-cloud-secret-manager (>=2.18.0)
Requires-Dist: google-cloud-storage (>=2.14.0)
Requires-Dist: google-cloud-tasks (>=2.16.0)
Requires-Dist: httpx (>=0.25.0)
Requires-Dist: jiwer (>=3.0.0)
Requires-Dist: karaoke-lyrics-processor (>=0.6)
Requires-Dist: kbputils (>=0.0.16,<0.0.17)
Requires-Dist: langchain (>=0.3.0)
Requires-Dist: langchain-anthropic (>=0.2.0)
Requires-Dist: langchain-core (>=0.3.0)
Requires-Dist: langchain-google-genai (>=2.0.0)
Requires-Dist: langchain-ollama (>=0.2.0)
Requires-Dist: langchain-openai (>=0.2.0)
Requires-Dist: langfuse (>=3.0.0)
Requires-Dist: langgraph (>=0.2.0)
Requires-Dist: lyrics-converter (>=0.2.1)
Requires-Dist: lyricsgenius (>=3)
Requires-Dist: matplotlib (>=3)
Requires-Dist: metaphone (>=0.6)
Requires-Dist: mutagen (>=1.47)
Requires-Dist: nest-asyncio (>=1.5)
Requires-Dist: nltk (>=3.9)
Requires-Dist: numpy (>=2)
Requires-Dist: ollama (>=0.4.7)
Requires-Dist: openai (>=1.63.2)
Requires-Dist: opentelemetry-api (>=1.20.0)
Requires-Dist: opentelemetry-exporter-gcp-trace (>=1.6.0)
Requires-Dist: opentelemetry-instrumentation-fastapi (>=0.41b0)
Requires-Dist: opentelemetry-instrumentation-httpx (>=0.41b0)
Requires-Dist: opentelemetry-instrumentation-logging (>=0.41b0)
Requires-Dist: opentelemetry-resourcedetector-gcp (>=1.6.0a0)
Requires-Dist: opentelemetry-sdk (>=1.20.0)
Requires-Dist: pillow (>=10.1)
Requires-Dist: psutil (>=7.0.0,<8.0.0)
Requires-Dist: pydantic (>=2.5.0)
Requires-Dist: pydantic-settings (>=2.1.0)
Requires-Dist: pydub (>=0.25.1)
Requires-Dist: pyinstaller (>=6.3)
Requires-Dist: pyperclip
Requires-Dist: pytest (>=7.0) ; extra == "dev"
Requires-Dist: pytest-asyncio
Requires-Dist: pytest-cov (>=4.0) ; extra == "dev"
Requires-Dist: pytest-mock (>=3.10) ; extra == "dev"
Requires-Dist: python-dotenv (>=1.0.0)
Requires-Dist: python-levenshtein (>=0.26)
Requires-Dist: python-multipart (>=0.0.20,<0.0.21)
Requires-Dist: python-slugify (>=8)
Requires-Dist: pywebpush (>=2.0.0)
Requires-Dist: requests (>=2)
Requires-Dist: sendgrid (>=6.10.0)
Requires-Dist: shortuuid (>=1.0.13)
Requires-Dist: spacy (>=3.8.7)
Requires-Dist: spacy-syllables (>=3)
Requires-Dist: srsly (>=2.5.1)
Requires-Dist: stripe (>=7.0.0)
Requires-Dist: syllables (>=1)
Requires-Dist: syrics (>=0)
Requires-Dist: thefuzz (>=0.22)
Requires-Dist: toml (>=0.10)
Requires-Dist: torch (>=2.7)
Requires-Dist: tqdm (>=4.67)
Requires-Dist: transformers (>=4.47)
Requires-Dist: uvicorn[standard] (>=0.24.0)
Requires-Dist: whisper-timestamped (>=1.15.0) ; extra == "local-whisper"
Requires-Dist: yt-dlp (>=2024.0.0)
Project-URL: Documentation, https://github.com/nomadkaraoke/karaoke-gen/blob/main/README.md
Project-URL: Homepage, https://github.com/nomadkaraoke/karaoke-gen
Project-URL: Repository, https://github.com/nomadkaraoke/karaoke-gen
